pypika/__init__.py
pypika/analytics.py
pypika/dialects.py
pypika/enums.py
pypika/functions.py
pypika/pseudocolumns.py
pypika/queries.py
pypika/terms.py
pypika/utils.py
XPyPika-0.14.9.dist-info/METADATA
XPyPika-0.14.9.dist-info/WHEEL
XPyPika-0.14.9.dist-info/top_level.txt
XPyPika-0.14.9.dist-info/RECORD
