Metadata-Version: 2.1
Name: XPyPika
Version: 0.14.9
Summary: A SQL query builder API for Python
Home-page: https://github.com/kayak/pypika
Author: Timothy Heys
Author-email: theys@kayak.com
License: Apache License Version 2.0
Platform: UNKNOWN
Requires-Dist: aenum (==2.0.8)
